pyexcel_xlsbr/__init__.py
pyexcel_xlsbr/_version.py
pyexcel_xlsbr/xlsbr.py
pyexcel_xlsbr-0.6.1.dist-info/LICENSE
pyexcel_xlsbr-0.6.1.dist-info/METADATA
pyexcel_xlsbr-0.6.1.dist-info/WHEEL
pyexcel_xlsbr-0.6.1.dist-info/top_level.txt
pyexcel_xlsbr-0.6.1.dist-info/RECORD
