Metadata-Version: 2.1
Name: pyexcel-xlsbr
Version: 0.6.1
Summary: read Microsoft Excel tm xlsb file
Home-page: https://github.com/pyexcel/pyexcel-xlsbr
Author: C.W.
Author-email: info@pyexcel.org
License: New BSD
Download-URL: https://github.com/pyexcel/pyexcel-xlsbr/archive/0.6.1.tar.gz
Keywords: python
Platform: UNKNOWN
Classifier: Topic :: Software Development :: Libraries
Classifier: Programming Language :: Python
Classifier: Intended Audience :: Developers
Classifier: Programming Language :: Python :: 3 :: Only
Classifier: Programming Language :: Python :: 3.6
Classifier: Programming Language :: Python :: 3.7
Classifier: Programming Language :: Python :: 3.8
Requires-Python: >=3.6
Requires-Dist: pyxlsb
Requires-Dist: pyexcel-io (>=0.6.0)
